mgcomm/__init__.py
mgcomm/_version.py
mgcomm/env.py
mgcomm/xdg.py
mgcomm-0.2.0.dist-info/DESCRIPTION.rst
mgcomm-0.2.0.dist-info/METADATA
mgcomm-0.2.0.dist-info/RECORD
mgcomm-0.2.0.dist-info/WHEEL
mgcomm-0.2.0.dist-info/metadata.json
mgcomm-0.2.0.dist-info/top_level.txt
