Metadata-Version: 2.0
Name: mgcomm
Version: 0.2.0
Summary: small utility library with handy fixtures
Home-page: https://gitlab.com/mgoral/mgcomm
Author: Michał Góral
Author-email: dev@mgoral.org
License: MIT
Platform: linux
Classifier: Development Status :: 2 - Pre-Alpha
Classifier: Environment :: Console
Classifier: Intended Audience :: Developers
Classifier: License :: OSI Approved :: MIT License
Classifier: Natural Language :: English
Classifier: Operating System :: POSIX
Classifier: Programming Language :: Python :: 3 :: Only
Classifier: Topic :: Software Development :: Libraries
Classifier: Topic :: Utilities
